Workbook

Sheet Sheet1
A1: Name | B1: Age | C1: Salary | D1: Date of joining | E1: Awarded | L1: vid 3 | U1: Product name | V1: Price | W1: Quantity | X1: Totel Cost | AA1: vid 4
A2: Harry | B2: 18 | C2: 25000 | D2: 45909 | E2: TRUE | U2: A | V2: 25 | W2: 2 | X2: =V2*W2 -> 50
A3: Ron | B3: 25 | C3: 15000 | D3: 45858 | E3: FALSE | U3: B | V3: 34 | W3: 3 | X3: =V3*W3 -> 102
A4: Lukus | B4: 36 | C4: 18000 | D4: 46078 | E4: FALSE | U4: C | V4: 26 | W4: 5 | X4: =V4*W4 -> 130
A5: Danny | B5: 29 | C5: 20000 | D5: 45612 | E5: TRUE | U5: D | V5: 58 | W5: 4 | X5: =V5*W5 -> 232
U6: Total | V6: =SUM(V2:V5) -> 143 | W6: =SUM(W2:W5) -> 14 | X6: =SUM(X2:X5) -> 514
U7: Avg | V7: =AVERAGE(V2:V5) -> 35.75
U8: Count | V8: =COUNT(V2:V5) -> 4
U9: MIN | V9: =MIN(V2:V5) -> 25
U10: MAX | V10: =MAX(V2:V5) -> 58

Sheet Cell Reference
B1: B | C1: C | D1: D | F1: 5
A2: 1 | B2: Product A | C2: Product B | D2: Product C | F2: 10
A3: 2 | B3: 100 | C3: 200 | D3: 300 | F3: 15
A4: 3 | B4: 150 | C4: 250 | D4: 350
A5: 4 | B5: 200 | C5: 300 | D5: 400

Sheet Sheet2
A1: Name | B1: sales | C1: cost | D1: profit
A2: Milk | B2: 150 | C2: 100 | D2: =B2-C2 -> 50
A3: Rise | B3: 500 | C3: 350 | D3: =B3-C3 -> 150
A4: egg | B4: 330 | C4: 175 | D4: =B4-C4 -> 155
A5: Chocolate | B5: 782 | C5: 600 | D5: =B5-C5 -> 182
A6: Brade | B6: 53 | C6: 45 | D6: =B6-C6 -> 8
B7: =SUM(B2:B6) -> 1815 | C7: =SUM(C2:C6) -> 1270 | D7: =D2+D3+D4+D5+D6 -> 545
G10: =B7-C7 -> 545

Sheet  Consolidation_Table1
A1: Month | B1: Sales | C1: Expences | D1: Profit
A2: Jan | B2: 55000 | C2: 30000 | D2: =B2-C2 -> 25000
A3: Feb | B3: 60000 | C3: 35000 | D3: =B3-C3 -> 25000
A4: Mar | B4: 55000 | C4: 32000 | D4: =B4-C4 -> 23000

Sheet  Consolidation_Table2
A1: Month | B1: Sales | C1: Expences | D1: Profit
A2: Jan | B2: 45000 | C2: 28000 | D2: =B2-C2 -> 17000
A3: Feb | B3: 52000 | C3: 30000 | D3: =B3-C3 -> 22000
A4: Mar | B4: 58000 | C4: 33000 | D4: =B4-C4 -> 25000

Sheet  Consolidation_Table3
A1: Month | B1: Sales | C1: Expences | D1: Profit
A2: Jan | B2: 40000 | C2: 25000 | D2: =B2-C2 -> 15000
A3: Feb | B3: 48000 | C3: 27000 | D3: =B3-C3 -> 21000
A4: Mar | B4: 51000 | C4: 29000 | D4: =B4-C4 -> 22000

Sheet  Consolidation_Summary
A1: Month | B1: Sales | C1: Expences | D1: Profit
A2: Jan | B2: =' Consolidation_Table1'!B2+' Consolidation_Table2'!B2+' Consolidation_Table3'!B2 -> 140000 | C2: =' Consolidation_Table1'!C2+' Consolidation_Table2'!C2+' Consolidation_Table3'!C2 -> 83000 | D2: =' Consolidation_Table1'!D2+' Consolidation_Table2'!D2+' Consolidation_Table3'!D2 -> 57000 | F2: This output from teble selaction
A3: Feb | B3: =' Consolidation_Table1'!B3+' Consolidation_Table2'!B3+' Consolidation_Table3'!B3 -> 160000 | C3: =' Consolidation_Table1'!C3+' Consolidation_Table2'!C3+' Consolidation_Table3'!C3 -> 92000 | D3: =' Consolidation_Table1'!D3+' Consolidation_Table2'!D3+' Consolidation_Table3'!D3 -> 68000
A4: Mar | B4: =' Consolidation_Table1'!B4+' Consolidation_Table2'!B4+' Consolidation_Table3'!B4 -> 164000 | C4: =' Consolidation_Table1'!C4+' Consolidation_Table2'!C4+' Consolidation_Table3'!C4 -> 94000 | D4: =' Consolidation_Table1'!D4+' Consolidation_Table2'!D4+' Consolidation_Table3'!D4 -> 70000
A9: Month | B9: Sales | C9: Expences | D9: Profit
A10: Jan | B10: 135000 | C10: 83000 | D10: 52000 | F10: This output from consolidation in data tab
A11: Feb | B11: 160000 | C11: 92000 | D11: 68000
A12: Mar | B12: 164000 | C12: 94000 | D12: 70000
